avnie/__init__.py
avnie/interactive.py
avnie/main.py
avnie-2025.12.18.dist-info/METADATA
avnie-2025.12.18.dist-info/WHEEL
avnie-2025.12.18.dist-info/entry_points.txt
avnie-2025.12.18.dist-info/licenses/LICENSE
avnie-2025.12.18.dist-info/RECORD
