Metadata-Version: 2.4
Name: avnie
Version: 2025.12.18
Summary: Command-line interface to avro.py; transliteration in the terminal.
Project-URL: Homepage, https://pypi.org/project/avnie
Project-URL: Repository, https://github.com/hitblast/avnie
Author: Anindya Shiddhartha
License-Expression: MIT
License-File: LICENSE
Keywords: avnie,avnie-cli,avro,avro phonetic,avro.py-cli,bangla,bengali,bengali phonetics,cli,command-line,command-line interface,phonetics,python,transliteration
Requires-Python: >=3.9
Requires-Dist: avro-py>=2025.8.11
Requires-Dist: click>=8.1.8
Requires-Dist: pyclip>=0.7.0
Requires-Dist: rich>=14.2.0
